[
  {
    "category": "UNIT_INTERACTION",
    "insight": "Chieftain functions as efficient soak against freeze threats (like Endotherm Kit) even if not attacking with it, and blocking with it when frozen is generally correct play.",
    "units": [
      "Chieftain",
      "Endotherm Kit"
    ],
    "confidence": "high",
    "author": "p0lari, tophwells",
    "date": "2018-04",
    "replay_code": "yttcc-KTUg0",
    "context": "Player analysis of early game freeze defense strategy.",
    "temporal_validity": "patch_dependent",
    "source_message_ids": [
      "2018-04-08 15:36",
      "2018-04-08 15:38"
    ]
  },
  {
    "category": "STRATEGY_RULE",
    "insight": "Freezing a single Matrix with opponent's Endotherm Kit resources (Bite + Cryo Charge) for only 2 damage is inefficient; the chill threat of 3 lifespan is more valuable than converting to immediate damage.",
    "units": [
      "Matrix",
      "Endotherm Kit"
    ],
    "confidence": "high",
    "author": "p0lari",
    "date": "2018-04",
    "replay_code": "yttcc-KTUg0",
    "context": "Discussion of when to use opponent's freeze resources vs. preserving chill threat.",
    "temporal_validity": "timeless",
    "source_message_ids": [
      "2018-04-08 16:34",
      "2018-04-08 16:35"
    ]
  },
  {
    "category": "OPENING_THEORY",
    "insight": "In sets with Thorium Dynamo, P2 can counter early double Dynamo with DD/1D opening to stay competitive in economy, avoiding an instaloss despite the eco boost.",
    "units": [
      "Thorium Dynamo"
    ],
    "confidence": "high",
    "author": ".bky_1556, amalloy",
    "date": "2018-04",
    "replay_code": null,
    "context": "Player asking how to punish AI's early double Dynamo opening.",
    "temporal_validity": "patch_dependent",
    "source_message_ids": [
      "2018-04-09 04:39",
      "2018-04-09 04:48"
    ]
  },
  {
    "category": "GAME_MECHANIC",
    "insight": "Thorium Dynamo is not playable when P1 can breach during the turn P2 has no tech and no income, or when 14-drone income is too slow for the set's tempo.",
    "units": [
      "Thorium Dynamo"
    ],
    "confidence": "high",
    "author": ".bky_1556",
    "date": "2018-04",
    "replay_code": null,
    "context": "Discussion of when Thorium is and is not a viable tech investment.",
    "temporal_validity": "patch_dependent",
    "source_message_ids": [
      "2018-04-09 04:51"
    ]
  },
  {
    "category": "GAME_MECHANIC",
    "insight": "Savior is viable when the set has good defense and P1 cannot punish a 3rd Engineer opening, and when no significant Red attacker (Big Red) appears before turn 9.",
    "units": [
      "Savior"
    ],
    "confidence": "high",
    "author": ".bky_1556",
    "date": "2018-04",
    "replay_code": null,
    "context": "Explanation of conditions under which Savior becomes a playable unit.",
    "temporal_validity": "patch_dependent",
    "source_message_ids": [
      "2018-04-09 04:52",
      "2018-04-09 04:57",
      "2018-04-09 04:58"
    ]
  },
  {
    "category": "STRATEGY_RULE",
    "insight": "Arms Race can be viable in a mutual-breach situation if the Omega Splitter is the best breach target, making it worth considering as a utility purchase.",
    "units": [
      "Arms Race",
      "Omega Splitter"
    ],
    "confidence": "medium",
    "author": ".bky_1556",
    "date": "2018-04",
    "replay_code": null,
    "context": "Brief comment on Arms Race viability in specific board states.",
    "temporal_validity": "patch_dependent",
    "source_message_ids": [
      "2018-04-09 00:46"
    ]
  },
  {
    "category": "UNIT_INTERACTION",
    "insight": "Blastforge + Pixie costs 6B for 1 damage, which is worse than Steelsplitter's 6B for 2 damage, making Steelsplitter the superior attacker.",
    "units": [
      "Blastforge",
      "Pixie",
      "Steelsplitter"
    ],
    "confidence": "high",
    "author": "shadourow",
    "date": "2018-04",
    "replay_code": null,
    "context": "Analysis of unit efficiency during game conclusion.",
    "temporal_validity": "timeless",
    "source_message_ids": [
      "2018-04-09 06:27"
    ]
  },
  {
    "category": "GAME_MECHANIC",
    "insight": "Supply levels for units follow a pattern: 1-2 attack units typically have 10 supply, 3+ attack units typically have 4 supply, with exceptions for units with special abilities or defensive properties.",
    "units": [],
    "confidence": "medium",
    "author": "apooche",
    "date": "2018-04",
    "replay_code": null,
    "context": "General discussion of unit supply balance philosophy.",
    "temporal_validity": "timeless",
    "source_message_ids": [
      "2018-04-09 18:21",
      "2018-04-09 18:23",
      "2018-04-09 18:24"
    ]
  },
  {
    "category": "UNIT_INTERACTION",
    "insight": "Grimbotch freeze decisions depend on absorber types: freezing 2LS Grimbotch with Vai is usually bad (loses tempo on offense), but can be correct if it forces opponent to sacrifice valuable defenders or blocks key unit interactions.",
    "units": [
      "Grimbotch",
      "Vai Mauronax"
    ],
    "confidence": "medium",
    "author": "apooche, .bky_1556",
    "date": "2018-04",
    "replay_code": null,
    "context": "Detailed analysis of freeze targeting strategy with Vai Mauronax.",
    "temporal_validity": "patch_dependent",
    "source_message_ids": [
      "2018-04-09 19:13",
      "2018-04-09 19:19",
      "2018-04-09 19:38"
    ]
  },
  {
    "category": "STRATEGY_RULE",
    "insight": "When freezing a Grimbotch with Vai to breach the opponent's best absorber, you can force them to choose suboptimal defense absorption (e.g., using Engineer instead of Borehole Patroller), gaining tempo advantage.",
    "units": [
      "Grimbotch",
      "Vai Mauronax",
      "Borehole Patroller"
    ],
    "confidence": "medium",
    "author": ".bky_1556",
    "date": "2018-04",
    "replay_code": null,
    "context": "Analysis of forcing opponent defense choices through freeze targeting.",
    "temporal_validity": "timeless",
    "source_message_ids": [
      "2018-04-09 19:18",
      "2018-04-09 19:39"
    ]
  },
  {
    "category": "GAME_MECHANIC",
    "insight": "With Thermite Core, if you have an odd amount of damage, you can click one Pixie to make damage even and activate all cores without wasting any damage value.",
    "units": [
      "Thermite Core",
      "Pixie"
    ],
    "confidence": "high",
    "author": ".bky_1556",
    "date": "2018-04",
    "replay_code": null,
    "context": "Pro tip for maximizing Thermite Core efficiency.",
    "temporal_validity": "patch_dependent",
    "source_message_ids": [
      "2018-04-09 19:54"
    ]
  },
  {
    "category": "UNIT_INTERACTION",
    "insight": "Mobile Animus (Manimus) synergizes well with Valkyrion for single-Iceblade-per-turn strategies, providing flexibility to sell red units late game; it is less efficient than full Animus but enables tactical flexibility.",
    "units": [
      "Mobile Animus",
      "Valkyrion"
    ],
    "confidence": "high",
    "author": "liadahlia, .bky_1556",
    "date": "2018-04",
    "replay_code": null,
    "context": "Comparison of Mobile Animus and full Animus in specific set contexts.",
    "temporal_validity": "patch_dependent",
    "source_message_ids": [
      "2018-04-10 00:16",
      "2018-04-10 00:17"
    ]
  },
  {
    "category": "BALANCE_OPINION",
    "insight": "Smorcus is a highly efficient attacker, nearly as strong as old Flame Animus Perforator combo (which was nerfed), with Animus click yielding roughly Omega Splitter efficiency or slightly better.",
    "units": [
      "Smorcus",
      "Animus",
      "Omega Splitter"
    ],
    "confidence": "high",
    "author": ".bky_1556",
    "date": "2018-04",
    "replay_code": "u3YRG-@VrTH",
    "context": "Analysis of Smorcus power level and efficiency comparisons.",
    "temporal_validity": "patch_dependent",
    "source_message_ids": [
      "2018-04-10 00:29",
      "2018-04-10 00:31",
      "2018-04-10 01:56"
    ]
  },
  {
    "category": "UNIT_INTERACTION",
    "insight": "Smorcus + Animus click combo costs 11RR for 2 attack and is a lightweight combo purchasable over 2 turns, making it an aggressive early option.",
    "units": [
      "Smorcus",
      "Animus"
    ],
    "confidence": "high",
    "author": ".bky_1556, Deleted User",
    "date": "2018-04",
    "replay_code": null,
    "context": "Discussion of Smorcus-Animus synergy efficiency and economy.",
    "temporal_validity": "patch_dependent",
    "source_message_ids": [
      "2018-04-10 00:28",
      "2018-04-10 00:33"
    ]
  },
  {
    "category": "GAME_MECHANIC",
    "insight": "1RR click ability on Smorcus breaks no-click-cycles with Auride Core, preventing situations where opponent can farm resources without threat.",
    "units": [
      "Smorcus",
      "Auride Core"
    ],
    "confidence": "high",
    "author": ".bky_1556",
    "date": "2018-04",
    "replay_code": null,
    "context": "Mechanical interaction of Smorcus click with Auride Core strategies.",
    "temporal_validity": "patch_dependent",
    "source_message_ids": [
      "2018-04-10 02:23"
    ]
  },
  {
    "category": "UNIT_INTERACTION",
    "insight": "Shiver Yeti with Valkyrion functions like an infinite-stamina Rhino with +1 threat, making it an extremely valuable synergy for permanent attack pressure.",
    "units": [
      "Shiver Yeti",
      "Valkyrion"
    ],
    "confidence": "high",
    "author": "p0lari, darkeisbein",
    "date": "2018-04",
    "replay_code": null,
    "context": "Analysis of Shiver Yeti utility with Valkyrion.",
    "temporal_validity": "patch_dependent",
    "source_message_ids": [
      "2018-04-10 08:29",
      "2018-04-10 08:30"
    ]
  },
  {
    "category": "STRATEGY_RULE",
    "insight": "Valkyrion + Cryo Ray is an auto-buy synergy when both are available; the 4G package cost for 2 Valk + 4 Cryo is efficient, with excess green easily converted to more Cryo.",
    "units": [
      "Valkyrion",
      "Cryo Ray"
    ],
    "confidence": "high",
    "author": "liadahlia, kristian1103",
    "date": "2018-04",
    "replay_code": null,
    "context": "Discussion of Valkyrion-Cryo Ray package efficiency and value.",
    "temporal_validity": "patch_dependent",
    "source_message_ids": [
      "2018-04-10 08:32",
      "2018-04-10 08:33",
      "2018-04-10 08:34"
    ]
  },
  {
    "category": "STRATEGY_RULE",
    "insight": "When holding all Valkyrions to avoid attacking (e.g., 4/0/4 pattern), you gain 3 free absorb denials while still defending the damage threat on the defense turn, making all-Valk rushes very efficient if you have no other permanent damage.",
    "units": [
      "Valkyrion"
    ],
    "confidence": "high",
    "author": "kristian1103, p0lari",
    "date": "2018-04",
    "replay_code": null,
    "context": "Analysis of Valkyrion holding patterns and absorb value.",
    "temporal_validity": "patch_dependent",
    "source_message_ids": [
      "2018-04-10 08:47",
      "2018-04-10 08:49",
      "2018-04-10 08:52"
    ]
  },
  {
    "category": "STRATEGY_RULE",
    "insight": "Holding Valkyrions every other turn (vs. every turn) becomes less efficient as you accumulate more Valkyrions, since each additional Valk yields diminishing absorb denial value.",
    "units": [
      "Valkyrion"
    ],
    "confidence": "medium",
    "author": "liadahlia",
    "date": "2018-04",
    "replay_code": null,
    "context": "Analysis of diminishing returns from multiple Valkyrion holds.",
    "temporal_validity": "timeless",
    "source_message_ids": [
      "2018-04-10 08:48"
    ]
  },
  {
    "category": "GAME_MECHANIC",
    "insight": "Mobile Animus costs 1 more gold than half an Animus, making it strictly less efficient for single Iceblade per turn compared to full Animus (which produces 2 Iceblades and can freeze a unit).",
    "units": [
      "Mobile Animus",
      "Animus"
    ],
    "confidence": "high",
    "author": "307th",
    "date": "2018-04",
    "replay_code": null,
    "context": "Developer analysis of Mobile Animus efficiency vs. traditional Animus.",
    "temporal_validity": "patch_dependent",
    "source_message_ids": [
      "2018-04-09 13:42"
    ]
  },
  {
    "category": "UNIT_INTERACTION",
    "insight": "Mobile Animus + Iceblade can be good in fastblade strategies against Red-heavy sets where traditional Animus provides a bigger upgrade than the standard build.",
    "units": [
      "Mobile Animus",
      "Iceblade",
      "Animus"
    ],
    "confidence": "medium",
    "author": "redrame",
    "date": "2018-04",
    "replay_code": null,
    "context": "Discussion of Mobile Animus situational utility in fast-blade strategies.",
    "temporal_validity": "patch_dependent",
    "source_message_ids": [
      "2018-04-09 15:17",
      "2018-04-09 15:18"
    ]
  },
  {
    "category": "GAME_MECHANIC",
    "insight": "Mahar Rectifier supply is high (10) because it functions as a primary attacker in situations where Animus is unavailable or undesirable, with 11GG/2 efficiency being acceptable for such scenarios.",
    "units": [
      "Mahar Rectifier",
      "Animus"
    ],
    "confidence": "medium",
    "author": ".bky_1556",
    "date": "2018-04",
    "replay_code": "qI@dm-HC+bd",
    "context": "Explanation of high supply on situational attacker unit.",
    "temporal_validity": "patch_dependent",
    "source_message_ids": [
      "2018-04-09 17:02"
    ]
  },
  {
    "category": "STRATEGY_RULE",
    "insight": "P1 T1 Attacker opening in base + Smorcus may be difficult for P2 to refute, suggesting the Smorcus combo is particularly strong at early aggressive pressure.",
    "units": [
      "Smorcus"
    ],
    "confidence": "medium",
    "author": ".bky_1556",
    "date": "2018-04",
    "replay_code": null,
    "context": "Analysis of early-game Smorcus pressure in base-set heavy games.",
    "temporal_validity": "patch_dependent",
    "source_message_ids": [
      "2018-04-10 02:05"
    ]
  }
]